{
  "collectionName": "components_checklist_check_similar_proejcts",
  "info": {
    "displayName": "checkSimilarProejcts",
    "description": ""
  },
  "options": {},
  "attributes": {
    "name": {
      "type": "text"
    },
    "text": {
      "type": "text"
    },
    "active": {
      "type": "boolean"
    },
    "sortPosition": {
      "type": "integer"
    },
    "file": {
      "type": "media",
      "multiple": true,
      "required": false,
      "allowedTypes": [
        "images",
        "files",
        "videos",
        "audios"
      ]
    },
    "tasks": {
      "type": "json"
    }
  }
}
